{
    "/jsx/application.js": "/jsx/application.js",
    "/jsx/application.d53cd87c021f64f90808.hot-update.js": "/jsx/application.d53cd87c021f64f90808.hot-update.js",
    "/jsx/application.2c49839dbf4e3e2c7ef9.hot-update.js": "/jsx/application.2c49839dbf4e3e2c7ef9.hot-update.js",
    "/jsx/application.2ceef2cef2d6d34ce0d3.hot-update.js": "/jsx/application.2ceef2cef2d6d34ce0d3.hot-update.js",
    "/jsx/application.1ff617c2105cf13e7ae3.hot-update.js": "/jsx/application.1ff617c2105cf13e7ae3.hot-update.js",
    "/jsx/application.8f277139fe2f17db9226.hot-update.js": "/jsx/application.8f277139fe2f17db9226.hot-update.js",
    "/jsx/application.04786e6dfe2e4776860f.hot-update.js": "/jsx/application.04786e6dfe2e4776860f.hot-update.js",
    "/jsx/application.4da31a9087c829aad88d.hot-update.js": "/jsx/application.4da31a9087c829aad88d.hot-update.js",
    "/jsx/application.ab52b76fda9b027a5973.hot-update.js": "/jsx/application.ab52b76fda9b027a5973.hot-update.js",
    "/jsx/application.ed94321e11d07caf2ee0.hot-update.js": "/jsx/application.ed94321e11d07caf2ee0.hot-update.js",
    "/jsx/application.e6b8c827dc40982e6239.hot-update.js": "/jsx/application.e6b8c827dc40982e6239.hot-update.js",
    "/jsx/application.834608b427aec5371f44.hot-update.js": "/jsx/application.834608b427aec5371f44.hot-update.js",
    "/jsx/application.52a5800b6005856dd5f5.hot-update.js": "/jsx/application.52a5800b6005856dd5f5.hot-update.js",
    "/jsx/application.1026e0c966bd225285be.hot-update.js": "/jsx/application.1026e0c966bd225285be.hot-update.js",
    "/jsx/application.48e73eefbb004efe46c7.hot-update.js": "/jsx/application.48e73eefbb004efe46c7.hot-update.js",
    "/jsx/application.a57a3993a3994a549149.hot-update.js": "/jsx/application.a57a3993a3994a549149.hot-update.js",
    "/jsx/application.7326905c33ed1b93cf1a.hot-update.js": "/jsx/application.7326905c33ed1b93cf1a.hot-update.js",
    "/jsx/application.35a6fd30080677c3dc4b.hot-update.js": "/jsx/application.35a6fd30080677c3dc4b.hot-update.js",
    "/jsx/application.d83c62de120386891e2f.hot-update.js": "/jsx/application.d83c62de120386891e2f.hot-update.js",
    "/jsx/application.9d35e70ac339a72c4057.hot-update.js": "/jsx/application.9d35e70ac339a72c4057.hot-update.js",
    "/jsx/application.2b235b7609d5bc4b6bc2.hot-update.js": "/jsx/application.2b235b7609d5bc4b6bc2.hot-update.js",
    "/jsx/application.98784877412c9c1438dc.hot-update.js": "/jsx/application.98784877412c9c1438dc.hot-update.js",
    "/jsx/application.cf05f955479294deab73.hot-update.js": "/jsx/application.cf05f955479294deab73.hot-update.js",
    "/jsx/application.4436c7c52d33476fe20c.hot-update.js": "/jsx/application.4436c7c52d33476fe20c.hot-update.js",
    "/jsx/application.ba04f9c7f56617315fbc.hot-update.js": "/jsx/application.ba04f9c7f56617315fbc.hot-update.js",
    "/jsx/application.e5cd37410bc9e6c6c087.hot-update.js": "/jsx/application.e5cd37410bc9e6c6c087.hot-update.js",
    "/jsx/application.6fd1a81ea77c71c31990.hot-update.js": "/jsx/application.6fd1a81ea77c71c31990.hot-update.js",
    "/jsx/application.222e76926505cf5e5b07.hot-update.js": "/jsx/application.222e76926505cf5e5b07.hot-update.js",
    "/jsx/application.e99189b8cafdaff17633.hot-update.js": "/jsx/application.e99189b8cafdaff17633.hot-update.js",
    "/jsx/application.5db857507a7f4dae25de.hot-update.js": "/jsx/application.5db857507a7f4dae25de.hot-update.js",
    "/jsx/application.1a42318b5c05c491e2d1.hot-update.js": "/jsx/application.1a42318b5c05c491e2d1.hot-update.js",
    "/jsx/application.989c65a2dd5a0d6b34a5.hot-update.js": "/jsx/application.989c65a2dd5a0d6b34a5.hot-update.js",
    "/jsx/application.a1b12a42edad721c7b32.hot-update.js": "/jsx/application.a1b12a42edad721c7b32.hot-update.js",
    "/jsx/application.6f1ca2090b7391089584.hot-update.js": "/jsx/application.6f1ca2090b7391089584.hot-update.js",
    "/jsx/application.e6e1785fa6089d404206.hot-update.js": "/jsx/application.e6e1785fa6089d404206.hot-update.js",
    "/jsx/application.6ab727388b80135c1c86.hot-update.js": "/jsx/application.6ab727388b80135c1c86.hot-update.js",
    "/jsx/application.cc075a4e9521d2e3f6d8.hot-update.js": "/jsx/application.cc075a4e9521d2e3f6d8.hot-update.js",
    "/jsx/application.de14e42a41cad5b340a4.hot-update.js": "/jsx/application.de14e42a41cad5b340a4.hot-update.js",
    "/jsx/application.7f90f6c73fe178a42e6c.hot-update.js": "/jsx/application.7f90f6c73fe178a42e6c.hot-update.js",
    "/jsx/application.1657e041f41a73b2179d.hot-update.js": "/jsx/application.1657e041f41a73b2179d.hot-update.js",
    "/jsx/application.a6f2f7f3af43eebc186b.hot-update.js": "/jsx/application.a6f2f7f3af43eebc186b.hot-update.js",
    "/jsx/application.5ae2f3e2d97271475ea7.hot-update.js": "/jsx/application.5ae2f3e2d97271475ea7.hot-update.js",
    "/jsx/application.eeecf94b8d9e31cc697e.hot-update.js": "/jsx/application.eeecf94b8d9e31cc697e.hot-update.js",
    "/jsx/application.0571ae999e32352dac35.hot-update.js": "/jsx/application.0571ae999e32352dac35.hot-update.js",
    "/jsx/application.a97de9bc953d17aa229b.hot-update.js": "/jsx/application.a97de9bc953d17aa229b.hot-update.js",
    "/jsx/application.2b7837dc1dc5d17a710c.hot-update.js": "/jsx/application.2b7837dc1dc5d17a710c.hot-update.js",
    "/jsx/application.de26ce063233b432536f.hot-update.js": "/jsx/application.de26ce063233b432536f.hot-update.js",
    "/jsx/application.e8db8064b79b877e2999.hot-update.js": "/jsx/application.e8db8064b79b877e2999.hot-update.js",
    "/jsx/application.47a4187826d64a20dae4.hot-update.js": "/jsx/application.47a4187826d64a20dae4.hot-update.js",
    "/jsx/application.ce9ec16da043b9a3541a.hot-update.js": "/jsx/application.ce9ec16da043b9a3541a.hot-update.js",
    "/jsx/application.c094f4b0d67ce9070c08.hot-update.js": "/jsx/application.c094f4b0d67ce9070c08.hot-update.js",
    "/jsx/application.39706dc0f08a07f5d101.hot-update.js": "/jsx/application.39706dc0f08a07f5d101.hot-update.js",
    "/jsx/application.f6dd1ed55bc34c0d15b9.hot-update.js": "/jsx/application.f6dd1ed55bc34c0d15b9.hot-update.js",
    "/jsx/application.36ff10c9f45a5d1a3547.hot-update.js": "/jsx/application.36ff10c9f45a5d1a3547.hot-update.js",
    "/jsx/application.ff0269fe64d4e9d3f4ea.hot-update.js": "/jsx/application.ff0269fe64d4e9d3f4ea.hot-update.js"
}
