{
    "/jsx/application.js": "/jsx/application.js",
    "/jsx/application.6d6e45bff18dc4e35bf5.hot-update.js": "/jsx/application.6d6e45bff18dc4e35bf5.hot-update.js",
    "/jsx/application.13e80925df848c1c73f9.hot-update.js": "/jsx/application.13e80925df848c1c73f9.hot-update.js",
    "/jsx/application.68151a8a23c56b40e329.hot-update.js": "/jsx/application.68151a8a23c56b40e329.hot-update.js",
    "/jsx/application.e8a5b01d21fbfac73b17.hot-update.js": "/jsx/application.e8a5b01d21fbfac73b17.hot-update.js",
    "/jsx/application.82caba85460d24f6b688.hot-update.js": "/jsx/application.82caba85460d24f6b688.hot-update.js",
    "/jsx/application.e3160269c418d89109bb.hot-update.js": "/jsx/application.e3160269c418d89109bb.hot-update.js",
    "/jsx/application.dd058fc698086df9af35.hot-update.js": "/jsx/application.dd058fc698086df9af35.hot-update.js",
    "/jsx/application.e8820c0cfb0e24742d4b.hot-update.js": "/jsx/application.e8820c0cfb0e24742d4b.hot-update.js",
    "/jsx/application.e4952924b144d44325fb.hot-update.js": "/jsx/application.e4952924b144d44325fb.hot-update.js"
}
