{
    "/jsx/application.js": "/jsx/application.js",
    "/jsx/application.46f695f0d7316f432160.hot-update.js": "/jsx/application.46f695f0d7316f432160.hot-update.js",
    "/jsx/application.c68edf0a86ec99d2466a.hot-update.js": "/jsx/application.c68edf0a86ec99d2466a.hot-update.js",
    "/jsx/application.e6d303391c2736d65069.hot-update.js": "/jsx/application.e6d303391c2736d65069.hot-update.js",
    "/jsx/application.806361fd802f1c037da5.hot-update.js": "/jsx/application.806361fd802f1c037da5.hot-update.js",
    "/jsx/application.70ee023429f96ed25b7c.hot-update.js": "/jsx/application.70ee023429f96ed25b7c.hot-update.js",
    "/jsx/application.5100e8b2756853daf5f0.hot-update.js": "/jsx/application.5100e8b2756853daf5f0.hot-update.js",
    "/jsx/application.1374c14c759e1633df1e.hot-update.js": "/jsx/application.1374c14c759e1633df1e.hot-update.js",
    "/jsx/application.d752df5e9bbb5fdefc83.hot-update.js": "/jsx/application.d752df5e9bbb5fdefc83.hot-update.js",
    "/jsx/application.6cd28b87a8b69ddd88ef.hot-update.js": "/jsx/application.6cd28b87a8b69ddd88ef.hot-update.js",
    "/jsx/application.d43768158d77bba10482.hot-update.js": "/jsx/application.d43768158d77bba10482.hot-update.js",
    "/jsx/application.cdbd2a38ba23d80dd650.hot-update.js": "/jsx/application.cdbd2a38ba23d80dd650.hot-update.js",
    "/jsx/application.553cba453b67bf322dfe.hot-update.js": "/jsx/application.553cba453b67bf322dfe.hot-update.js",
    "/jsx/application.161f6a1c1b2ec5b46cdc.hot-update.js": "/jsx/application.161f6a1c1b2ec5b46cdc.hot-update.js",
    "/jsx/application.e65d57af33ff7bf8836f.hot-update.js": "/jsx/application.e65d57af33ff7bf8836f.hot-update.js",
    "/jsx/application.69cf222656224be6612b.hot-update.js": "/jsx/application.69cf222656224be6612b.hot-update.js",
    "/jsx/application.709cb4e718448fc50b97.hot-update.js": "/jsx/application.709cb4e718448fc50b97.hot-update.js",
    "/jsx/application.a24690106ea5608edd39.hot-update.js": "/jsx/application.a24690106ea5608edd39.hot-update.js",
    "/jsx/application.0e739be7c8884461f2da.hot-update.js": "/jsx/application.0e739be7c8884461f2da.hot-update.js",
    "/jsx/application.a18d82a1e7f50545a661.hot-update.js": "/jsx/application.a18d82a1e7f50545a661.hot-update.js",
    "/jsx/application.fdbca5430d43e4e6c598.hot-update.js": "/jsx/application.fdbca5430d43e4e6c598.hot-update.js",
    "/jsx/application.03560117608c26dd9f77.hot-update.js": "/jsx/application.03560117608c26dd9f77.hot-update.js",
    "/jsx/application.87daafb0db9ab4239e67.hot-update.js": "/jsx/application.87daafb0db9ab4239e67.hot-update.js",
    "/jsx/application.ed605009fcb2df818324.hot-update.js": "/jsx/application.ed605009fcb2df818324.hot-update.js",
    "/jsx/application.4205e25e4c7c21d673f3.hot-update.js": "/jsx/application.4205e25e4c7c21d673f3.hot-update.js",
    "/jsx/application.777d54d7e5bcb905d6f3.hot-update.js": "/jsx/application.777d54d7e5bcb905d6f3.hot-update.js",
    "/jsx/application.b88cc3b649cc1d8f20e0.hot-update.js": "/jsx/application.b88cc3b649cc1d8f20e0.hot-update.js",
    "/jsx/application.fb7d12ae106d6d60b035.hot-update.js": "/jsx/application.fb7d12ae106d6d60b035.hot-update.js",
    "/jsx/application.76325cff46f29b6e2c19.hot-update.js": "/jsx/application.76325cff46f29b6e2c19.hot-update.js",
    "/jsx/application.5ca05a898b4f96941da7.hot-update.js": "/jsx/application.5ca05a898b4f96941da7.hot-update.js",
    "/jsx/application.48bf655f5aec7111a110.hot-update.js": "/jsx/application.48bf655f5aec7111a110.hot-update.js",
    "/jsx/application.3588725517731dc3278d.hot-update.js": "/jsx/application.3588725517731dc3278d.hot-update.js",
    "/jsx/application.9966dc17667b51ab027d.hot-update.js": "/jsx/application.9966dc17667b51ab027d.hot-update.js",
    "/jsx/application.46a6ef9e4fdfcc063826.hot-update.js": "/jsx/application.46a6ef9e4fdfcc063826.hot-update.js",
    "/jsx/application.19a2c85b688277bae6e3.hot-update.js": "/jsx/application.19a2c85b688277bae6e3.hot-update.js",
    "/jsx/application.a293ed0d31752fb58946.hot-update.js": "/jsx/application.a293ed0d31752fb58946.hot-update.js",
    "/jsx/application.d807d697e8b54154bf0b.hot-update.js": "/jsx/application.d807d697e8b54154bf0b.hot-update.js",
    "/jsx/application.dc1958f20e59f347a718.hot-update.js": "/jsx/application.dc1958f20e59f347a718.hot-update.js",
    "/jsx/application.4bb9d7b25ef48fc01d0f.hot-update.js": "/jsx/application.4bb9d7b25ef48fc01d0f.hot-update.js",
    "/jsx/application.8cf55a2c35dbcdf8fbd8.hot-update.js": "/jsx/application.8cf55a2c35dbcdf8fbd8.hot-update.js",
    "/jsx/application.876877194ee0d68dc266.hot-update.js": "/jsx/application.876877194ee0d68dc266.hot-update.js",
    "/jsx/application.a1ec63af7e69e47ce97f.hot-update.js": "/jsx/application.a1ec63af7e69e47ce97f.hot-update.js",
    "/jsx/application.e0af2b86b1b704178b6d.hot-update.js": "/jsx/application.e0af2b86b1b704178b6d.hot-update.js",
    "/jsx/application.e8737de8106ef6a01bd1.hot-update.js": "/jsx/application.e8737de8106ef6a01bd1.hot-update.js",
    "/jsx/application.16869ab95d3cbf31da3b.hot-update.js": "/jsx/application.16869ab95d3cbf31da3b.hot-update.js",
    "/jsx/application.dc384be1157f99d04a05.hot-update.js": "/jsx/application.dc384be1157f99d04a05.hot-update.js",
    "/jsx/application.ca4a0179125ddfb7ba38.hot-update.js": "/jsx/application.ca4a0179125ddfb7ba38.hot-update.js",
    "/jsx/application.59b4ecd9f025757e1f9b.hot-update.js": "/jsx/application.59b4ecd9f025757e1f9b.hot-update.js",
    "/jsx/application.118c4e8db69b8962f313.hot-update.js": "/jsx/application.118c4e8db69b8962f313.hot-update.js",
    "/jsx/application.f73b3878393d353b9c1f.hot-update.js": "/jsx/application.f73b3878393d353b9c1f.hot-update.js",
    "/jsx/application.9ec52e2bfaff53c863c8.hot-update.js": "/jsx/application.9ec52e2bfaff53c863c8.hot-update.js",
    "/jsx/application.025e11bb0b8223945bd6.hot-update.js": "/jsx/application.025e11bb0b8223945bd6.hot-update.js",
    "/jsx/application.3c1e0dafdb618e77c710.hot-update.js": "/jsx/application.3c1e0dafdb618e77c710.hot-update.js",
    "/jsx/application.4ff2f4e26e583718f8bf.hot-update.js": "/jsx/application.4ff2f4e26e583718f8bf.hot-update.js",
    "/jsx/application.c01b1ee8811d89e7dcfa.hot-update.js": "/jsx/application.c01b1ee8811d89e7dcfa.hot-update.js",
    "/jsx/application.c2217eb4b285f04c27d4.hot-update.js": "/jsx/application.c2217eb4b285f04c27d4.hot-update.js",
    "/jsx/application.0f9674ea243f2c78c7f5.hot-update.js": "/jsx/application.0f9674ea243f2c78c7f5.hot-update.js",
    "/jsx/application.c3bdbea441e33bc9968b.hot-update.js": "/jsx/application.c3bdbea441e33bc9968b.hot-update.js",
    "/jsx/application.0ec0b1614fc327854b74.hot-update.js": "/jsx/application.0ec0b1614fc327854b74.hot-update.js",
    "/jsx/application.835927f9495fe1d3f734.hot-update.js": "/jsx/application.835927f9495fe1d3f734.hot-update.js",
    "/jsx/application.ca7e9e0c6ee600417b1d.hot-update.js": "/jsx/application.ca7e9e0c6ee600417b1d.hot-update.js",
    "/jsx/application.f4ca027931cb061967aa.hot-update.js": "/jsx/application.f4ca027931cb061967aa.hot-update.js",
    "/jsx/application.7b8ace4edbe1da7f5cbb.hot-update.js": "/jsx/application.7b8ace4edbe1da7f5cbb.hot-update.js"
}
